{
  "device": "openaps://raspberrypi", 
  "pump": {
    "battery": {
      "status": "normal", 
      "voltage": 1.54
    }, 
    "status": {
      "status": "normal", 
      "timestamp": "2016-07-17T06:56:06.000Z", 
      "bolusing": false, 
      "suspended": false
    }, 
    "reservoir": 0, 
    "clock": "2016-06-30T22:50:55-07:00"
  }, 
  "openaps": {
    "suggested": {
      "bg": 132, 
      "temp": "absolute", 
      "snoozeBG": 120, 
      "timestamp": "2016-07-17T06:55:55.000Z", 
      "rate": 2, 
      "reason": "Eventual BG 120>=120, 26m@2.200 = 0.953 > req 0.34+0.1U", 
      "eventualBG": 120, 
      "duration": 30, 
      "mealAssist": "Off: Carbs: undefined Boluses: undefined ISF: 30, Target: 105 Deviation: 5 BGI: -2.72", 
      "tick": -1
    }, 
    "iob": {
      "netbasalinsulin": 0.05, 
      "timestamp": "2016-07-17T06:55:48.000Z", 
      "activity": 0.0181, 
      "basaliob": 0.064, 
      "hightempinsulin": 0.6, 
      "bolussnooze": 0, 
      "iob": 0.566
    }, 
    "enacted": {
      "bg": 132, 
      "temp": "absolute", 
      "snoozeBG": 120, 
      "recieved": true, 
      "reason": "Eventual BG 120>=120, 26m@2.200 = 0.953 > req 0.34+0.1U", 
      "rate": 2, 
      "eventualBG": 120, 
      "timestamp": "2016-07-17T06:56:00.000Z", 
      "duration": 30, 
      "mealAssist": "Off: Carbs: undefined Boluses: undefined ISF: 30, Target: 105 Deviation: 5 BGI: -2.72", 
      "tick": -1
    }
  }
}