[
  {
    "trend_arrow": "FLAT", 
    "system_time": "2016-07-15T00:57:32", 
    "display_time": "2016-07-14T17:55:52", 
    "glucose": 117
  }, 
  {
    "trend_arrow": "FLAT", 
    "system_time": "2016-07-15T00:52:32", 
    "display_time": "2016-07-14T17:50:52", 
    "glucose": 121
  }, 
  {
    "trend_arrow": "FLAT", 
    "system_time": "2016-07-11T11:57:46", 
    "display_time": "2016-07-11T04:56:06", 
    "glucose": 149
  }, 
  {
    "trend_arrow": "FLAT", 
    "system_time": "2016-07-11T11:52:51", 
    "display_time": "2016-07-11T04:51:10", 
    "glucose": 144
  }, 
  {
    "trend_arrow": "FLAT", 
    "system_time": "2016-07-11T11:47:52", 
    "display_time": "2016-07-11T04:46:12", 
    "glucose": 144
  }
]