[
  {
    "_id": "5763aa46ad448d473a26ea75",
    "sgv": 255,
    "date": 1466149400000,
    "dateString": "2016-06-17T07:43:20.000Z",
    "trend": 4,
    "direction": "Flat",
    "device": "share2",
    "type": "sgv",
    "glucose": 255
  },
  {
    "_id": "5763a7eead448d473a26ea74",
    "sgv": 259,
    "date": 1466148777000,
    "dateString": "2016-06-17T07:32:57.000Z",
    "trend": 4,
    "direction": "Flat",
    "device": "share2",
    "type": "sgv",
    "glucose": 259
  },
  {
    "_id": "5763a6c2ad448d473a26ea73",
    "sgv": 259,
    "date": 1466148477000,
    "dateString": "2016-06-17T07:27:57.000Z",
    "trend": 4,
    "direction": "Flat",
    "device": "share2",
    "type": "sgv",
    "glucose": 259
  },
  {
    "_id": "5763a597ad448d473a26ea72",
    "sgv": 260,
    "date": 1466148176000,
    "dateString": "2016-06-17T07:22:56.000Z",
    "trend": 4,
    "direction": "Flat",
    "device": "share2",
    "type": "sgv",
    "glucose": 260
  },
  {
    "_id": "5763a46bad448d473a26ea71",
    "sgv": 258,
    "date": 1466147877000,
    "dateString": "2016-06-17T07:17:57.000Z",
    "trend": 4,
    "direction": "Flat",
    "device": "share2",
    "type": "sgv",
    "glucose": 258
  },
  {
    "_id": "5763a33ead448d473a26ea70",
    "sgv": 257,
    "date": 1466147578000,
    "dateString": "2016-06-17T07:12:58.000Z",
    "trend": 4,
    "direction": "Flat",
    "device": "share2",
    "type": "sgv",
    "glucose": 257
  },
  {
    "_id": "5763a1e4ad448d473a26ea6f",
    "sgv": 255,
    "date": 1466147277000,
    "dateString": "2016-06-17T07:07:57.000Z",
    "trend": 4,
    "direction": "Flat",
    "device": "share2",
    "type": "sgv",
    "glucose": 255
  },
  {
    "_id": "5763a0b4ad448d473a26ea6d",
    "sgv": 253,
    "date": 1466146980000,
    "dateString": "2016-06-17T07:03:00.000Z",
    "trend": 4,
    "direction": "Flat",
    "device": "share2",
    "type": "sgv",
    "glucose": 253
  },
  {
    "_id": "57639f88ad448d473a26ea6c",
    "sgv": 251,
    "date": 1466146680000,
    "dateString": "2016-06-17T06:58:00.000Z",
    "trend": 4,
    "direction": "Flat",
    "device": "share2",
    "type": "sgv",
    "glucose": 251
  },
  {
    "_id": "57639e5cad448d473a26ea6b",
    "sgv": 248,
    "date": 1466146381000,
    "dateString": "2016-06-17T06:53:01.000Z",
    "trend": 4,
    "direction": "Flat",
    "device": "share2",
    "type": "sgv",
    "glucose": 248
  }
]
