[
  {
    "_id": "576c29442ac0a07cf65fcc1e",
    "sgv": 120,
    "date": 1466706154000,
    "dateString": "2016-06-23T18:22:34.000Z",
    "trend": 4,
    "direction": "Flat",
    "device": "share2",
    "type": "sgv",
    "glucose": 120
  },
  {
    "_id": "576c28192ac0a07cf65fcc1a",
    "sgv": 122,
    "date": 1466705859000,
    "dateString": "2016-06-23T18:17:39.000Z",
    "trend": 4,
    "direction": "Flat",
    "device": "share2",
    "type": "sgv",
    "glucose": 122
  },
  {
    "_id": "576c26ec2ac0a07cf65fcc19",
    "sgv": 127,
    "date": 1466705555000,
    "dateString": "2016-06-23T18:12:35.000Z",
    "trend": 4,
    "direction": "Flat",
    "device": "share2",
    "type": "sgv",
    "glucose": 127
  },
  {
    "_id": "576c25c02ac0a07cf65fcc15",
    "sgv": 127,
    "date": 1466705256000,
    "dateString": "2016-06-23T18:07:36.000Z",
    "trend": 4,
    "direction": "Flat",
    "device": "share2",
    "type": "sgv",
    "glucose": 127
  },
  {
    "_id": "576c24942ac0a07cf65fcc14",
    "sgv": 130,
    "date": 1466704955000,
    "dateString": "2016-06-23T18:02:35.000Z",
    "trend": 4,
    "direction": "Flat",
    "device": "share2",
    "type": "sgv",
    "glucose": 130
  },
  {
    "_id": "576c23682ac0a07cf65fcc11",
    "sgv": 131,
    "date": 1466704655000,
    "dateString": "2016-06-23T17:57:35.000Z",
    "trend": 4,
    "direction": "Flat",
    "device": "share2",
    "type": "sgv",
    "glucose": 131
  },
  {
    "_id": "576c21102ac0a07cf65fcc0c",
    "sgv": 131,
    "date": 1466704059000,
    "dateString": "2016-06-23T17:47:39.000Z",
    "trend": 4,
    "direction": "Flat",
    "device": "share2",
    "type": "sgv",
    "glucose": 131
  },
  {
    "_id": "576c1fe42ac0a07cf65fcc0b",
    "sgv": 127,
    "date": 1466703755000,
    "dateString": "2016-06-23T17:42:35.000Z",
    "trend": 4,
    "direction": "Flat",
    "device": "share2",
    "type": "sgv",
    "glucose": 127
  },
  {
    "_id": "576c1eb82ac0a07cf65fcc04",
    "sgv": 133,
    "date": 1466703454000,
    "dateString": "2016-06-23T17:37:34.000Z",
    "trend": 4,
    "direction": "Flat",
    "device": "share2",
    "type": "sgv",
    "glucose": 133
  },
  {
    "_id": "576c1d8c2ac0a07cf65fcc03",
    "sgv": 137,
    "date": 1466703157000,
    "dateString": "2016-06-23T17:32:37.000Z",
    "trend": 4,
    "direction": "Flat",
    "device": "share2",
    "type": "sgv",
    "glucose": 137
  }
]
