[
  {
    "_id": "57710b692ac0a07cf66016e2",
    "sgv": 386,
    "date": 1467026244000,
    "dateString": "2016-06-27T11:17:24.000Z",
    "trend": 4,
    "direction": "Flat",
    "device": "share2",
    "type": "sgv",
    "glucose": 386
  },
  {
    "_id": "57710a3d2ac0a07cf66016e1",
    "sgv": 383,
    "date": 1467025942000,
    "dateString": "2016-06-27T11:12:22.000Z",
    "trend": 4,
    "direction": "Flat",
    "device": "share2",
    "type": "sgv",
    "glucose": 383
  },
  {
    "_id": "577109112ac0a07cf66015c0",
    "sgv": 378,
    "date": 1467025643000,
    "dateString": "2016-06-27T11:07:23.000Z",
    "trend": 4,
    "direction": "Flat",
    "device": "share2",
    "type": "sgv",
    "glucose": 378
  },
  {
    "_id": "577107e52ac0a07cf66013a3",
    "sgv": 376,
    "date": 1467025344000,
    "dateString": "2016-06-27T11:02:24.000Z",
    "trend": 4,
    "direction": "Flat",
    "device": "share2",
    "type": "sgv",
    "glucose": 376
  },
  {
    "_id": "577106b92ac0a07cf6601186",
    "sgv": 372,
    "date": 1467025042000,
    "dateString": "2016-06-27T10:57:22.000Z",
    "trend": 4,
    "direction": "Flat",
    "device": "share2",
    "type": "sgv",
    "glucose": 372
  },
  {
    "_id": "5771058d2ac0a07cf6600f69",
    "sgv": 368,
    "date": 1467024744000,
    "dateString": "2016-06-27T10:52:24.000Z",
    "trend": 4,
    "direction": "Flat",
    "device": "share2",
    "type": "sgv",
    "glucose": 368
  },
  {
    "_id": "577104602ac0a07cf6600d4c",
    "sgv": 366,
    "date": 1467024445000,
    "dateString": "2016-06-27T10:47:25.000Z",
    "trend": 3,
    "direction": "FortyFiveUp",
    "device": "share2",
    "type": "sgv",
    "glucose": 366
  },
  {
    "_id": "577103342ac0a07cf6600b2f",
    "sgv": 367,
    "date": 1467024144000,
    "dateString": "2016-06-27T10:42:24.000Z",
    "trend": 3,
    "direction": "FortyFiveUp",
    "device": "share2",
    "type": "sgv",
    "glucose": 367
  },
  {
    "_id": "577102082ac0a07cf6600912",
    "sgv": 362,
    "date": 1467023845000,
    "dateString": "2016-06-27T10:37:25.000Z",
    "trend": 3,
    "direction": "FortyFiveUp",
    "device": "share2",
    "type": "sgv",
    "glucose": 362
  },
  {
    "_id": "577100dc2ac0a07cf6600827",
    "sgv": 354,
    "date": 1467023544000,
    "dateString": "2016-06-27T10:32:24.000Z",
    "trend": 3,
    "direction": "FortyFiveUp",
    "device": "share2",
    "type": "sgv",
    "glucose": 354
  }
]
