[
  {
    "_id": "578b9a7c2ac0a07cf66179ab",
    "sgv": 111,
    "date": 1468766777000,
    "dateString": "2016-07-17T14:46:17.000Z",
    "trend": 4,
    "direction": "Flat",
    "device": "share2",
    "type": "sgv",
    "glucose": 111
  },
  {
    "_id": "578b99502ac0a07cf66179aa",
    "sgv": 105,
    "date": 1468766475000,
    "dateString": "2016-07-17T14:41:15.000Z",
    "trend": 4,
    "direction": "Flat",
    "device": "share2",
    "type": "sgv",
    "glucose": 105
  },
  {
    "_id": "578b98242ac0a07cf66179a9",
    "sgv": 106,
    "date": 1468766178000,
    "dateString": "2016-07-17T14:36:18.000Z",
    "trend": 4,
    "direction": "Flat",
    "device": "share2",
    "type": "sgv",
    "glucose": 106
  },
  {
    "_id": "578b96f82ac0a07cf66179a7",
    "sgv": 105,
    "date": 1468765874000,
    "dateString": "2016-07-17T14:31:14.000Z",
    "trend": 4,
    "direction": "Flat",
    "device": "share2",
    "type": "sgv",
    "glucose": 105
  },
  {
    "_id": "578b95cc2ac0a07cf66179a6",
    "sgv": 105,
    "date": 1468765573000,
    "dateString": "2016-07-17T14:26:13.000Z",
    "trend": 4,
    "direction": "Flat",
    "device": "share2",
    "type": "sgv",
    "glucose": 105
  },
  {
    "_id": "578b94a02ac0a07cf66179a4",
    "sgv": 104,
    "date": 1468765275000,
    "dateString": "2016-07-17T14:21:15.000Z",
    "trend": 4,
    "direction": "Flat",
    "device": "share2",
    "type": "sgv",
    "glucose": 104
  },
  {
    "_id": "578b93742ac0a07cf66179a3",
    "sgv": 104,
    "date": 1468764974000,
    "dateString": "2016-07-17T14:16:14.000Z",
    "trend": 4,
    "direction": "Flat",
    "device": "share2",
    "type": "sgv",
    "glucose": 104
  },
  {
    "_id": "578b92482ac0a07cf66179a2",
    "sgv": 105,
    "date": 1468764677000,
    "dateString": "2016-07-17T14:11:17.000Z",
    "trend": 4,
    "direction": "Flat",
    "device": "share2",
    "type": "sgv",
    "glucose": 105
  },
  {
    "_id": "578b911c2ac0a07cf66179a1",
    "sgv": 113,
    "date": 1468764379000,
    "dateString": "2016-07-17T14:06:19.000Z",
    "trend": 4,
    "direction": "Flat",
    "device": "share2",
    "type": "sgv",
    "glucose": 113
  },
  {
    "_id": "578b8ff02ac0a07cf661799e",
    "sgv": 115,
    "date": 1468764076000,
    "dateString": "2016-07-17T14:01:16.000Z",
    "trend": 4,
    "direction": "Flat",
    "device": "share2",
    "type": "sgv",
    "glucose": 115
  }
]
