[
  {
    "trend_arrow": "FLAT", 
    "system_time": "2016-07-24T14:21:55", 
    "display_time": "2016-07-24T07:20:14", 
    "glucose": 81
  }, 
  {
    "trend_arrow": "FLAT", 
    "system_time": "2016-07-24T14:16:55", 
    "display_time": "2016-07-24T07:15:14", 
    "glucose": 83
  }, 
  {
    "trend_arrow": "FLAT", 
    "system_time": "2016-07-24T14:11:55", 
    "display_time": "2016-07-24T07:10:14", 
    "glucose": 85
  }, 
  {
    "trend_arrow": "FLAT", 
    "system_time": "2016-07-24T14:06:56", 
    "display_time": "2016-07-24T07:05:16", 
    "glucose": 87
  }, 
  {
    "trend_arrow": "FLAT", 
    "system_time": "2016-07-24T14:01:59", 
    "display_time": "2016-07-24T07:00:19", 
    "glucose": 88
  }
]