[
  {
    "_id": "577119792ac0a07cf66016ed",
    "sgv": 401,
    "date": 1467029845000,
    "dateString": "2016-06-27T12:17:25.000Z",
    "trend": 4,
    "direction": "Flat",
    "device": "share2",
    "type": "sgv",
    "glucose": 401
  },
  {
    "_id": "5771184d2ac0a07cf66016ec",
    "sgv": 401,
    "date": 1467029544000,
    "dateString": "2016-06-27T12:12:24.000Z",
    "trend": 4,
    "direction": "Flat",
    "device": "share2",
    "type": "sgv",
    "glucose": 401
  },
  {
    "_id": "577117212ac0a07cf66016eb",
    "sgv": 401,
    "date": 1467029245000,
    "dateString": "2016-06-27T12:07:25.000Z",
    "trend": 4,
    "direction": "Flat",
    "device": "share2",
    "type": "sgv",
    "glucose": 401
  },
  {
    "_id": "577115f52ac0a07cf66016ea",
    "sgv": 401,
    "date": 1467028945000,
    "dateString": "2016-06-27T12:02:25.000Z",
    "trend": 4,
    "direction": "Flat",
    "device": "share2",
    "type": "sgv",
    "glucose": 401
  },
  {
    "_id": "577114c92ac0a07cf66016e9",
    "sgv": 401,
    "date": 1467028645000,
    "dateString": "2016-06-27T11:57:25.000Z",
    "trend": 4,
    "direction": "Flat",
    "device": "share2",
    "type": "sgv",
    "glucose": 401
  },
  {
    "_id": "5771139d2ac0a07cf66016e8",
    "sgv": 401,
    "date": 1467028343000,
    "dateString": "2016-06-27T11:52:23.000Z",
    "trend": 4,
    "direction": "Flat",
    "device": "share2",
    "type": "sgv",
    "glucose": 401
  },
  {
    "_id": "577112712ac0a07cf66016e7",
    "sgv": 401,
    "date": 1467028047000,
    "dateString": "2016-06-27T11:47:27.000Z",
    "trend": 4,
    "direction": "Flat",
    "device": "share2",
    "type": "sgv",
    "glucose": 401
  },
  {
    "_id": "577111452ac0a07cf66016e6",
    "sgv": 401,
    "date": 1467027748000,
    "dateString": "2016-06-27T11:42:28.000Z",
    "trend": 3,
    "direction": "FortyFiveUp",
    "device": "share2",
    "type": "sgv",
    "glucose": 401
  },
  {
    "_id": "577110192ac0a07cf66016e5",
    "sgv": 401,
    "date": 1467027443000,
    "dateString": "2016-06-27T11:37:23.000Z",
    "trend": 3,
    "direction": "FortyFiveUp",
    "device": "share2",
    "type": "sgv",
    "glucose": 401
  },
  {
    "_id": "57710dc12ac0a07cf66016e4",
    "sgv": 394,
    "date": 1467026844000,
    "dateString": "2016-06-27T11:27:24.000Z",
    "trend": 3,
    "direction": "FortyFiveUp",
    "device": "share2",
    "type": "sgv",
    "glucose": 394
  }
]
