[
  {
    "_id": "577e81042ac0a07cf66131b2",
    "sgv": 139,
    "date": 1467908208000,
    "dateString": "2016-07-07T16:16:48.000Z",
    "trend": 4,
    "direction": "Flat",
    "device": "share2",
    "type": "sgv",
    "glucose": 139
  },
  {
    "_id": "577e7fd82ac0a07cf66131ae",
    "sgv": 140,
    "date": 1467907909000,
    "dateString": "2016-07-07T16:11:49.000Z",
    "trend": 4,
    "direction": "Flat",
    "device": "share2",
    "type": "sgv",
    "glucose": 140
  },
  {
    "_id": "577e7eac2ac0a07cf66131ad",
    "sgv": 140,
    "date": 1467907607000,
    "dateString": "2016-07-07T16:06:47.000Z",
    "trend": 4,
    "direction": "Flat",
    "device": "share2",
    "type": "sgv",
    "glucose": 140
  },
  {
    "_id": "577e7d802ac0a07cf66131a9",
    "sgv": 136,
    "date": 1467907308000,
    "dateString": "2016-07-07T16:01:48.000Z",
    "trend": 4,
    "direction": "Flat",
    "device": "share2",
    "type": "sgv",
    "glucose": 136
  },
  {
    "_id": "577e7c542ac0a07cf66131a6",
    "sgv": 133,
    "date": 1467907010000,
    "dateString": "2016-07-07T15:56:50.000Z",
    "trend": 4,
    "direction": "Flat",
    "device": "share2",
    "type": "sgv",
    "glucose": 133
  },
  {
    "_id": "577e7b282ac0a07cf66131a3",
    "sgv": 133,
    "date": 1467906711000,
    "dateString": "2016-07-07T15:51:51.000Z",
    "trend": 4,
    "direction": "Flat",
    "device": "share2",
    "type": "sgv",
    "glucose": 133
  },
  {
    "_id": "577e79fc2ac0a07cf66131a0",
    "sgv": 130,
    "date": 1467906411000,
    "dateString": "2016-07-07T15:46:51.000Z",
    "trend": 4,
    "direction": "Flat",
    "device": "share2",
    "type": "sgv",
    "glucose": 130
  },
  {
    "_id": "577e78d02ac0a07cf661319d",
    "sgv": 128,
    "date": 1467906109000,
    "dateString": "2016-07-07T15:41:49.000Z",
    "trend": 4,
    "direction": "Flat",
    "device": "share2",
    "type": "sgv",
    "glucose": 128
  },
  {
    "_id": "577e77a42ac0a07cf661319a",
    "sgv": 126,
    "date": 1467905809000,
    "dateString": "2016-07-07T15:36:49.000Z",
    "trend": 4,
    "direction": "Flat",
    "device": "share2",
    "type": "sgv",
    "glucose": 126
  },
  {
    "_id": "577e76782ac0a07cf6613195",
    "sgv": 124,
    "date": 1467905508000,
    "dateString": "2016-07-07T15:31:48.000Z",
    "trend": 4,
    "direction": "Flat",
    "device": "share2",
    "type": "sgv",
    "glucose": 124
  }
]
