[
  {
    "_id": "578699922ac0a07cf6615521",
    "sgv": 113,
    "date": 1468438887000,
    "dateString": "2016-07-13T19:41:27.000Z",
    "trend": 4,
    "direction": "Flat",
    "device": "share2",
    "type": "sgv",
    "glucose": 113
  },
  {
    "_id": "578698662ac0a07cf661551e",
    "sgv": 113,
    "date": 1468438586000,
    "dateString": "2016-07-13T19:36:26.000Z",
    "trend": 4,
    "direction": "Flat",
    "device": "share2",
    "type": "sgv",
    "glucose": 113
  },
  {
    "_id": "5786973a2ac0a07cf661551b",
    "sgv": 117,
    "date": 1468438286000,
    "dateString": "2016-07-13T19:31:26.000Z",
    "trend": 4,
    "direction": "Flat",
    "device": "share2",
    "type": "sgv",
    "glucose": 117
  },
  {
    "_id": "5786960e2ac0a07cf6615517",
    "sgv": 118,
    "date": 1468437987000,
    "dateString": "2016-07-13T19:26:27.000Z",
    "trend": 4,
    "direction": "Flat",
    "device": "share2",
    "type": "sgv",
    "glucose": 118
  },
  {
    "_id": "578694e22ac0a07cf6615514",
    "sgv": 118,
    "date": 1468437689000,
    "dateString": "2016-07-13T19:21:29.000Z",
    "trend": 4,
    "direction": "Flat",
    "device": "share2",
    "type": "sgv",
    "glucose": 118
  },
  {
    "_id": "578693b62ac0a07cf6615511",
    "sgv": 116,
    "date": 1468437387000,
    "dateString": "2016-07-13T19:16:27.000Z",
    "trend": 4,
    "direction": "Flat",
    "device": "share2",
    "type": "sgv",
    "glucose": 116
  },
  {
    "_id": "5786928a2ac0a07cf661550e",
    "sgv": 117,
    "date": 1468437088000,
    "dateString": "2016-07-13T19:11:28.000Z",
    "trend": 4,
    "direction": "Flat",
    "device": "share2",
    "type": "sgv",
    "glucose": 117
  },
  {
    "_id": "5786915e2ac0a07cf661550b",
    "sgv": 116,
    "date": 1468436787000,
    "dateString": "2016-07-13T19:06:27.000Z",
    "trend": 4,
    "direction": "Flat",
    "device": "share2",
    "type": "sgv",
    "glucose": 116
  },
  {
    "_id": "578690322ac0a07cf6615508",
    "sgv": 114,
    "date": 1468436487000,
    "dateString": "2016-07-13T19:01:27.000Z",
    "trend": 4,
    "direction": "Flat",
    "device": "share2",
    "type": "sgv",
    "glucose": 114
  },
  {
    "_id": "57868f062ac0a07cf6615504",
    "sgv": 114,
    "date": 1468436190000,
    "dateString": "2016-07-13T18:56:30.000Z",
    "trend": 4,
    "direction": "Flat",
    "device": "share2",
    "type": "sgv",
    "glucose": 114
  }
]
