[
  {
    "_id": "5781c5302ac0a07cf66139ba",
    "sgv": 145,
    "date": 1468122400000,
    "dateString": "2016-07-10T03:46:40.000Z",
    "trend": 3,
    "direction": "FortyFiveUp",
    "device": "share2",
    "type": "sgv",
    "glucose": 145
  },
  {
    "_id": "5781c4042ac0a07cf66139b9",
    "sgv": 142,
    "date": 1468122101000,
    "dateString": "2016-07-10T03:41:41.000Z",
    "trend": 3,
    "direction": "FortyFiveUp",
    "device": "share2",
    "type": "sgv",
    "glucose": 142
  },
  {
    "_id": "5781bf542ac0a07cf66139b7",
    "sgv": 123,
    "date": 1468120909000,
    "dateString": "2016-07-10T03:21:49.000Z",
    "trend": 4,
    "direction": "Flat",
    "device": "share2",
    "type": "sgv",
    "glucose": 123
  },
  {
    "_id": "5781bcfc2ac0a07cf66139a8",
    "sgv": 116,
    "date": 1468120300000,
    "dateString": "2016-07-10T03:11:40.000Z",
    "trend": 4,
    "direction": "Flat",
    "device": "share2",
    "type": "sgv",
    "glucose": 116
  },
  {
    "_id": "5781bbd02ac0a07cf66139a7",
    "sgv": 116,
    "date": 1468120000000,
    "dateString": "2016-07-10T03:06:40.000Z",
    "trend": 4,
    "direction": "Flat",
    "device": "share2",
    "type": "sgv",
    "glucose": 116
  },
  {
    "_id": "5781baa42ac0a07cf66139a6",
    "sgv": 119,
    "date": 1468119704000,
    "dateString": "2016-07-10T03:01:44.000Z",
    "trend": 4,
    "direction": "Flat",
    "device": "share2",
    "type": "sgv",
    "glucose": 119
  },
  {
    "_id": "5781b9782ac0a07cf66139a5",
    "sgv": 123,
    "date": 1468119400000,
    "dateString": "2016-07-10T02:56:40.000Z",
    "trend": 4,
    "direction": "Flat",
    "device": "share2",
    "type": "sgv",
    "glucose": 123
  },
  {
    "_id": "5781b84c2ac0a07cf66139a4",
    "sgv": 124,
    "date": 1468119101000,
    "dateString": "2016-07-10T02:51:41.000Z",
    "trend": 4,
    "direction": "Flat",
    "device": "share2",
    "type": "sgv",
    "glucose": 124
  },
  {
    "_id": "5781b7202ac0a07cf66139a3",
    "sgv": 124,
    "date": 1468118811000,
    "dateString": "2016-07-10T02:46:51.000Z",
    "trend": 4,
    "direction": "Flat",
    "device": "share2",
    "type": "sgv",
    "glucose": 124
  },
  {
    "_id": "5781b4c82ac0a07cf66139a2",
    "sgv": 126,
    "date": 1468118208000,
    "dateString": "2016-07-10T02:36:48.000Z",
    "trend": 4,
    "direction": "Flat",
    "device": "share2",
    "type": "sgv",
    "glucose": 126
  }
]
