[
  {
    "_id": "576445e9ad448d473a27ae9b",
    "sgv": 150,
    "date": 1466189275000,
    "dateString": "2016-06-17T18:47:55.000Z",
    "trend": 4,
    "direction": "Flat",
    "device": "share2",
    "type": "sgv",
    "glucose": 150
  },
  {
    "_id": "576444bdad448d473a27ae98",
    "sgv": 151,
    "date": 1466188977000,
    "dateString": "2016-06-17T18:42:57.000Z",
    "trend": 4,
    "direction": "Flat",
    "device": "share2",
    "type": "sgv",
    "glucose": 151
  },
  {
    "_id": "57644391ad448d473a27ae95",
    "sgv": 152,
    "date": 1466188679000,
    "dateString": "2016-06-17T18:37:59.000Z",
    "trend": 4,
    "direction": "Flat",
    "device": "share2",
    "type": "sgv",
    "glucose": 152
  },
  {
    "_id": "5764426bad448d473a27ae8f",
    "sgv": 153,
    "date": 1466188375000,
    "dateString": "2016-06-17T18:32:55.000Z",
    "trend": 4,
    "direction": "Flat",
    "device": "share2",
    "type": "sgv",
    "glucose": 153
  },
  {
    "_id": "57644139ad448d473a27ae8e",
    "sgv": 158,
    "date": 1466188076000,
    "dateString": "2016-06-17T18:27:56.000Z",
    "trend": 4,
    "direction": "Flat",
    "device": "share2",
    "type": "sgv",
    "glucose": 158
  },
  {
    "_id": "5764400dad448d473a27ae8c",
    "sgv": 160,
    "date": 1466187776000,
    "dateString": "2016-06-17T18:22:56.000Z",
    "trend": 4,
    "direction": "Flat",
    "device": "share2",
    "type": "sgv",
    "glucose": 160
  },
  {
    "_id": "57643ee1ad448d473a27ae88",
    "sgv": 161,
    "date": 1466187476000,
    "dateString": "2016-06-17T18:17:56.000Z",
    "trend": 4,
    "direction": "Flat",
    "device": "share2",
    "type": "sgv",
    "glucose": 161
  },
  {
    "_id": "57643db5ad448d473a27ae85",
    "sgv": 163,
    "date": 1466187175000,
    "dateString": "2016-06-17T18:12:55.000Z",
    "trend": 4,
    "direction": "Flat",
    "device": "share2",
    "type": "sgv",
    "glucose": 163
  },
  {
    "_id": "57643c89ad448d473a27ae82",
    "sgv": 165,
    "date": 1466186875000,
    "dateString": "2016-06-17T18:07:55.000Z",
    "trend": 4,
    "direction": "Flat",
    "device": "share2",
    "type": "sgv",
    "glucose": 165
  },
  {
    "_id": "57643b5dad448d473a27ae80",
    "sgv": 167,
    "date": 1466186579000,
    "dateString": "2016-06-17T18:02:59.000Z",
    "trend": 4,
    "direction": "Flat",
    "device": "share2",
    "type": "sgv",
    "glucose": 167
  }
]
