{
  "device": "openaps://raspberrypi", 
  "pump": {
    "battery": {
      "status": "normal", 
      "voltage": 1.33
    }, 
    "status": {
      "status": "normal", 
      "timestamp": "2016-06-30T17:46:15.000Z", 
      "bolusing": false, 
      "suspended": false
    }, 
    "reservoir": 59.2, 
    "clock": "2016-06-30T10:46:11"
  }, 
  "openaps": {
    "suggested": {
      "bg": 136, 
      "temp": "absolute", 
      "snoozeBG": 127, 
      "timestamp": "2016-06-30T17:46:04.000Z", 
      "rate": 2.6, 
      "reason": "Eventual BG 127>=110, temp 1.8<2.6U/hr", 
      "eventualBG": 127, 
      "duration": 30, 
      "mealAssist": "Off: Carbs: undefined Boluses: undefined ISF: 30, Target: 100 Deviation: 18 BGI: -2.61", 
      "tick": "+4"
    }, 
    "iob": {
      "netbasalinsulin": 2.1, 
      "timestamp": "2016-06-30T17:45:57.000Z", 
      "activity": 0.0174, 
      "basaliob": 0.888, 
      "hightempinsulin": 2.15, 
      "bolussnooze": 0, 
      "iob": 0.903
    }, 
    "enacted": {
      "bg": 136, 
      "temp": "absolute", 
      "snoozeBG": 127, 
      "recieved": true, 
      "reason": "Eventual BG 127>=110, temp 1.8<2.6U/hr", 
      "rate": 2.6, 
      "eventualBG": 127, 
      "timestamp": "2016-06-30T17:46:09.000Z", 
      "duration": 30, 
      "mealAssist": "Off: Carbs: undefined Boluses: undefined ISF: 30, Target: 100 Deviation: 18 BGI: -2.61", 
      "tick": "+4"
    }
  }
}