{
  "device": "openaps://raspberrypi", 
  "pump": {
    "battery": {
      "status": "normal", 
      "voltage": 1.33
    }, 
    "status": {
      "status": "normal", 
      "timestamp": "2016-07-05T22:30:59.000Z", 
      "bolusing": false, 
      "suspended": false
    }, 
    "reservoir": 221.5, 
    "clock": "2016-07-05T15:31:08"
  }, 
  "openaps": {
    "suggested": {
      "bg": 191, 
      "temp": "absolute", 
      "snoozeBG": 242, 
      "timestamp": "2016-07-05T22:30:53.000Z", 
      "reason": "Eventual BG -116<90, bolus snooze: eventual BG range -116-242, temp 1.175 ~ req 1.2U/hr", 
      "eventualBG": -116, 
      "mealAssist": "Off: Carbs: undefined Boluses: undefined ISF: 30, Target: 105 Deviation: -2 BGI: -6.36", 
      "tick": -11
    }, 
    "iob": {
      "netbasalinsulin": 0, 
      "timestamp": "2016-07-05T22:30:46.000Z", 
      "activity": 0.0424, 
      "basaliob": 0, 
      "hightempinsulin": 0, 
      "bolussnooze": 7.946, 
      "iob": 10.179
    }, 
    "enacted": {
      "bg": 202, 
      "temp": "absolute", 
      "snoozeBG": 298, 
      "recieved": true, 
      "reason": "Eventual BG -91<90, bolus snooze: eventual BG range -91-298; setting current basal of 1.2 as temp. Setting neutral temp basal of 1.2U/hr", 
      "rate": 1.175, 
      "eventualBG": -91, 
      "timestamp": "2016-07-05T22:26:37.000Z", 
      "duration": 30, 
      "mealAssist": "Off: Carbs: undefined Boluses: undefined ISF: 30, Target: 105 Deviation: 18 BGI: -5.28", 
      "tick": -7
    }
  }
}