{
  "device": "openaps://raspberrypi", 
  "pump": {
    "battery": {
      "status": "normal", 
      "voltage": 1.32
    }, 
    "status": {
      "status": "normal", 
      "timestamp": "2016-07-06T08:16:13.000Z", 
      "bolusing": false, 
      "suspended": false
    }, 
    "reservoir": 195.2, 
    "clock": "2016-07-06T01:16:22"
  }, 
  "openaps": {
    "suggested": {
      "bg": 157, 
      "temp": "absolute", 
      "snoozeBG": 128, 
      "timestamp": "2016-07-06T08:16:08.000Z", 
      "reason": "Eventual BG 128>=120, temp 2.1 >~ req 1.64U/hr", 
      "eventualBG": 128, 
      "mealAssist": "Off: Carbs: undefined Boluses: undefined ISF: 30, Target: 105 Deviation: 1 BGI: -2.49", 
      "tick": -2
    }, 
    "iob": {
      "netbasalinsulin": 1.9, 
      "timestamp": "2016-07-06T08:16:01.000Z", 
      "activity": 0.0166, 
      "basaliob": 0.988, 
      "hightempinsulin": 3, 
      "bolussnooze": 0, 
      "iob": 1.008
    }, 
    "enacted": {
      "bg": 161, 
      "temp": "absolute", 
      "snoozeBG": 135, 
      "recieved": true, 
      "reason": "Eventual BG 135>=120, temp 0<2.12U/hr", 
      "rate": 2.1, 
      "eventualBG": 135, 
      "timestamp": "2016-07-06T08:06:01.000Z", 
      "duration": 30, 
      "mealAssist": "Off: Carbs: undefined Boluses: undefined ISF: 30, Target: 105 Deviation: 3 BGI: -2.55", 
      "tick": -1
    }
  }
}