{
  "device": "openaps://raspberrypi", 
  "pump": {
    "battery": {
      "status": "normal", 
      "voltage": 1.29
    }, 
    "status": {
      "status": "normal", 
      "timestamp": "2016-07-07T10:46:09.000Z", 
      "bolusing": false, 
      "suspended": false
    }, 
    "reservoir": 131.3, 
    "clock": "2016-07-07T03:46:12"
  }, 
  "openaps": {
    "suggested": {
      "bg": 109, 
      "temp": "absolute", 
      "snoozeBG": 73, 
      "timestamp": "2016-07-07T10:45:59.000Z", 
      "rate": 0, 
      "reason": "Eventual BG 73<90, setting -4.267U/hr. Setting neutral temp basal of 0U/hr", 
      "eventualBG": 73, 
      "duration": 30, 
      "mealAssist": "Off: Carbs: undefined Boluses: undefined ISF: 30, Target: 105 Deviation: 7 BGI: -2.26", 
      "tick": "+0"
    }, 
    "iob": {
      "netbasalinsulin": 3, 
      "timestamp": "2016-07-07T10:45:52.000Z", 
      "activity": 0.0151, 
      "basaliob": 1.42, 
      "hightempinsulin": 3, 
      "bolussnooze": 0, 
      "iob": 1.42
    }, 
    "enacted": {
      "bg": 109, 
      "temp": "absolute", 
      "snoozeBG": 73, 
      "recieved": true, 
      "reason": "Eventual BG 73<90, setting -4.267U/hr. Setting neutral temp basal of 0U/hr", 
      "rate": 0, 
      "eventualBG": 73, 
      "timestamp": "2016-07-07T10:46:04.000Z", 
      "duration": 30, 
      "mealAssist": "Off: Carbs: undefined Boluses: undefined ISF: 30, Target: 105 Deviation: 7 BGI: -2.26", 
      "tick": "+0"
    }
  }
}