{
  "device": "openaps://raspberrypi", 
  "pump": {
    "battery": {
      "status": "normal", 
      "voltage": 1.25
    }, 
    "status": {
      "status": "normal", 
      "timestamp": "2016-07-07T19:51:19.000Z", 
      "bolusing": false, 
      "suspended": true
    }, 
    "reservoir": 110, 
    "clock": "2016-07-07T12:51:15"
  }, 
  "openaps": {
    "suggested": {
      "bg": 153, 
      "temp": "absolute", 
      "snoozeBG": 32, 
      "timestamp": "2016-07-07T19:51:02.000Z", 
      "rate": 0, 
      "reason": "Eventual BG 24<90, Snooze BG 32, setting -6.94U/hr", 
      "eventualBG": 24, 
      "duration": 30, 
      "mealAssist": "Off: Carbs: undefined Boluses: undefined ISF: 30, Target: 105 Deviation: 15 BGI: -15.25", 
      "tick": -4
    }, 
    "iob": {
      "netbasalinsulin": 1.55, 
      "timestamp": "2016-07-07T19:50:55.000Z", 
      "activity": 0.1017, 
      "basaliob": 0.465, 
      "hightempinsulin": 1.85, 
      "bolussnooze": 0.18, 
      "iob": 4.79
    }, 
    "enacted": {
      "requested": {
        "duration": 30, 
        "rate": 0, 
        "temp": "absolute"
      }, 
      "bg": 153, 
      "temp": "absolute", 
      "snoozeBG": 32, 
      "timestamp": "2016-07-07T19:51:14.000Z", 
      "reason": "Eventual BG 24<90, Snooze BG 32, setting -6.94U/hr", 
      "rate": 3.2, 
      "eventualBG": 24, 
      "recieved": false, 
      "duration": 0, 
      "mealAssist": "Off: Carbs: undefined Boluses: undefined ISF: 30, Target: 105 Deviation: 15 BGI: -15.25", 
      "tick": -4
    }
  }
}