{
  "device": "openaps://raspberrypi", 
  "pump": {
    "battery": {
      "status": "normal", 
      "voltage": 1.24
    }, 
    "status": {
      "status": "normal", 
      "timestamp": "2016-07-04T02:05:59.000Z", 
      "bolusing": false, 
      "suspended": false
    }, 
    "reservoir": 37.4, 
    "clock": "2016-07-03T19:06:06"
  }, 
  "openaps": {
    "suggested": [
      {
        "msg": "BG data is too old, or clock set incorrectly Sun Jul 03 2016 18:47:02 GMT-0700 (PDT) vs Sun Jul 03 2016 19:05:53 GMT-0700 (PDT)"
      }
    ], 
    "iob": {
      "netbasalinsulin": 0, 
      "timestamp": "2016-07-04T02:05:46.000Z", 
      "activity": 0.0625, 
      "basaliob": 0, 
      "hightempinsulin": 0, 
      "bolussnooze": 3.528, 
      "iob": 6.341
    }, 
    "enacted": {
      "bg": 158, 
      "temp": "absolute", 
      "snoozeBG": 96, 
      "recieved": true, 
      "reason": "Eventual BG 44<90, bolus snooze: eventual BG range 44-96; setting current basal of 1.2 as temp. Setting neutral temp basal of 1.2U/hr", 
      "rate": 1.175, 
      "eventualBG": 44, 
      "timestamp": "2016-07-04T01:51:06.000Z", 
      "duration": 30, 
      "mealAssist": "Off: Carbs: undefined Boluses: undefined ISF: 30, Target: 100 Deviation: 14 BGI: -9.61", 
      "tick": -4
    }
  }
}