{
  "device": "openaps://raspberrypi", 
  "pump": {
    "battery": {
      "status": "normal", 
      "voltage": 1.29
    }, 
    "status": {
      "status": "normal", 
      "timestamp": "2016-07-07T06:21:03.000Z", 
      "bolusing": false, 
      "suspended": false
    }, 
    "reservoir": 136.1, 
    "clock": "2016-07-06T23:21:08"
  }, 
  "openaps": {
    "suggested": {
      "bg": 132, 
      "temp": "absolute", 
      "snoozeBG": 139, 
      "timestamp": "2016-07-07T06:20:52.000Z", 
      "rate": 3.55, 
      "reason": "Eventual BG 139>=120, temp 0<3.567U/hr", 
      "eventualBG": 139, 
      "duration": 30, 
      "mealAssist": "Off: Carbs: undefined Boluses: undefined ISF: 30, Target: 105 Deviation: 11 BGI: -0.78", 
      "tick": "+4"
    }, 
    "iob": {
      "netbasalinsulin": -0.35, 
      "timestamp": "2016-07-07T06:20:45.000Z", 
      "activity": 0.0052, 
      "basaliob": 0.088, 
      "hightempinsulin": 0.65, 
      "bolussnooze": 0, 
      "iob": 0.12
    }, 
    "enacted": {
      "bg": 132, 
      "temp": "absolute", 
      "snoozeBG": 139, 
      "recieved": true, 
      "reason": "Eventual BG 139>=120, temp 0<3.567U/hr", 
      "rate": 3.525, 
      "eventualBG": 139, 
      "timestamp": "2016-07-07T06:20:58.000Z", 
      "duration": 30, 
      "mealAssist": "Off: Carbs: undefined Boluses: undefined ISF: 30, Target: 105 Deviation: 11 BGI: -0.78", 
      "tick": "+4"
    }
  }
}